[
  {
    "email": "john@example.com",
    "password": "password",
    "first_name": "John",
    "last_name": "Doe",
    "stub_data": true,
    "friends": [
      "alice@example.com",
      "bob@example.com"
    ]
  },
  {
    "email": "alice@example.com",
    "password": "password",
    "first_name": "Alice",
    "last_name": "Jones",
    "stub_data": true,
    "friends": [
      "john@example.com"
    ]
  },
  {
    "email": "bob@example.com",
    "password": "password",
    "first_name": "Bob",
    "last_name": "Smith",
    "stub_data": true,
    "friends": [
      "john@example.com"
    ]
  },
  {
    "email": "emma@example.com",
    "password": "password",
    "first_name": "Emma",
    "last_name": "Johnson",
    "stub_data": true,
    "friends": []
  },
  {
    "email": "mike@example.com",
    "password": "password",
    "first_name": "Mike",
    "last_name": "Smith",
    "stub_data": true,
    "friends": []
  }
]